scripts/__init__.py
scripts/example_auto_boost.py
scripts/example_flet_dashboard.py
scripts/example_jam.py
scripts/example_score.py
scripts/example_smooth.py
scripts/example_suggest.py
smooth_criminal/__init__.py
smooth_criminal/analizer.py
smooth_criminal/benchmark.py
smooth_criminal/cli.py
smooth_criminal/core.py
smooth_criminal/dashboard.py
smooth_criminal/memory.py
smooth_criminal/flet_app/components.py
smooth_criminal/flet_app/main.py
smooth_criminal/flet_app/utils.py
smooth_criminal/flet_app/views.py
smooth_criminal-0.7.0.dist-info/licenses/LICENSE.txt
smooth_criminal-0.7.0.dist-info/METADATA
smooth_criminal-0.7.0.dist-info/WHEEL
smooth_criminal-0.7.0.dist-info/top_level.txt
smooth_criminal-0.7.0.dist-info/RECORD
