Metadata-Version: 2.4
Name: smooth-criminal
Version: 0.7.0
Summary: Dashboard de análisis de rendimiento con decoradores inteligentes
Home-page: https://github.com/Alphonsus411/smooth_criminal
Author: Adolfo González
Author-email: Adolfo González <tucorreo@example.com>
License: MIT License
Project-URL: Homepage, https://github.com/Alphonsus411/smooth_criminal
Project-URL: Documentation, https://smooth-criminal.readthedocs.io/en/latest/
Classifier: Programming Language :: Python :: 3
Classifier: License :: OSI Approved :: MIT License
Classifier: Operating System :: OS Independent
Requires-Python: >=3.8
License-File: LICENSE.txt
Provides-Extra: tinydb
Requires-Dist: tinydb; extra == "tinydb"
Provides-Extra: sqlite
Dynamic: author
Dynamic: home-page
Dynamic: license-file
Dynamic: requires-python
